_ccv.so
ccv/__init__.py
ccv/face_detect.py
ccv/util.py
ccv-0.0.5.dist-info/DESCRIPTION.rst
ccv-0.0.5.dist-info/METADATA
ccv-0.0.5.dist-info/RECORD
ccv-0.0.5.dist-info/WHEEL
ccv-0.0.5.dist-info/metadata.json
ccv-0.0.5.dist-info/top_level.txt
