Metadata-Version: 2.0
Name: ccv
Version: 0.0.5
Summary: FFI bindings to libccv
Home-page: https://github.com/gpip/py-ccv
Author: Guilherme Polo
Author-email: gp@instaprint.me
License: UNKNOWN
Platform: UNKNOWN
Classifier: Intended Audience :: Developers
Classifier: Programming Language :: Python :: 2
Classifier: Programming Language :: Python :: Implementation :: CPython
Classifier: Topic :: Software Development :: Libraries
Requires-Dist: cffi (>=1.3.0)
Provides-Extra: util
Requires-Dist: Pillow (==3.2.0); extra == 'util'
